{
  "userCouponList": [],
  "paymentInstrumentList": [
    {
      "paymentInstrumentType": 2,
      "paymentInstrumentNo": "QAI00000000000019099",
      "paymentTitle": "建设银行(6555)",
      "cardNo": "621700*********6555",
      "cardType": 1,
      "bankName": "建设银行",
      "bankNo": "01050000",
      "bankLogoUrl": "https://iqcms.hdfax.com/eif-cms/app/bank/newLogo/CBC76x76.png",
      "singleLimit": "单笔限额400万 单日限额2000万 单月限额10000万",
      "singleLimitAmount": "4000000.00",
      "mobilePhone": "155****5555",
      "isAvailable": 1
    },
    {
      "paymentInstrumentType": 2,
      "paymentInstrumentNo": "QAI00000000000020656",
      "paymentTitle": "农业银行(6222)",
      "cardNo": "622848*********6222",
      "cardType": 1,
      "bankName": "农业银行",
      "bankNo": "01030000",
      "bankLogoUrl": "https://iqcms.hdfax.com/eif-cms/app/bank/newLogo/ABC76x76.png",
      "singleLimit": "单笔限额100万",
      "singleLimitAmount": "1000000.00",
      "mobilePhone": "111****1111",
      "isAvailable": 1
    },
    {
      "paymentInstrumentType": 2,
      "paymentInstrumentNo": "QAI00000000000021345",
      "paymentTitle": "工商银行(6111)",
      "cardNo": "621226*********6111",
      "cardType": 1,
      "bankName": "工商银行",
      "bankNo": "01020000",
      "bankLogoUrl": "https://iqcms.hdfax.com/eif-cms/app/bank/newLogo/ICBC76x76.png",
      "singleLimit": "单笔限额30万 单日限额400万 单月限额6000万",
      "singleLimitAmount": "300000.00",
      "mobilePhone": "155****1245",
      "isAvailable": 1
    }
  ],
  "availablePaymentList": [
    {
      "paymentInstrumentType": 2,
      "paymentInstrumentNo": "QAI00000000000019099",
      "paymentTitle": "建设银行(6555)",
      "cardNo": "621700*********6555",
      "cardType": 1,
      "bankName": "建设银行",
      "bankNo": "01050000",
      "bankLogoUrl": "https://iqcms.hdfax.com/eif-cms/app/bank/newLogo/CBC76x76.png",
      "singleLimit": "单笔限额400万 单日限额2000万 单月限额10000万",
      "singleLimitAmount": "4000000.00",
      "mobilePhone": "155****5555",
      "isAvailable": 1
    },
    {
      "paymentInstrumentType": 2,
      "paymentInstrumentNo": "QAI00000000000019099",
      "paymentTitle": "建设银行(6555)",
      "cardNo": "621700*********6555",
      "cardType": 1,
      "bankName": "建设银行",
      "bankNo": "01050000",
      "bankLogoUrl": "https://iqcms.hdfax.com/eif-cms/app/bank/newLogo/CBC76x76.png",
      "singleLimit": "单笔限额400万 单日限额2000万 单月限额10000万",
      "singleLimitAmount": "4000000.00",
      "mobilePhone": "155****5555",
      "isAvailable": 1
    },
    {
      "paymentInstrumentType": 2,
      "paymentInstrumentNo": "QAI00000000000019099",
      "paymentTitle": "建设银行(6555)",
      "cardNo": "621700*********6555",
      "cardType": 1,
      "bankName": "建设银行",
      "bankNo": "01050000",
      "bankLogoUrl": "https://iqcms.hdfax.com/eif-cms/app/bank/newLogo/CBC76x76.png",
      "singleLimit": "单笔限额400万 单日限额2000万 单月限额10000万",
      "singleLimitAmount": "4000000.00",
      "mobilePhone": "155****5555",
      "isAvailable": 1
    },
    {
      "paymentInstrumentType": 2,
      "paymentInstrumentNo": "QAI00000000000019099",
      "paymentTitle": "建设银行(6555)",
      "cardNo": "621700*********6555",
      "cardType": 1,
      "bankName": "建设银行",
      "bankNo": "01050000",
      "bankLogoUrl": "https://iqcms.hdfax.com/eif-cms/app/bank/newLogo/CBC76x76.png",
      "singleLimit": "单笔限额400万 单日限额2000万 单月限额10000万",
      "singleLimitAmount": "4000000.00",
      "mobilePhone": "155****5555",
      "isAvailable": 1
    },
    {
      "paymentInstrumentType": 2,
      "paymentInstrumentNo": "QAI00000000000019099",
      "paymentTitle": "建设银行(6555)",
      "cardNo": "621700*********6555",
      "cardType": 1,
      "bankName": "建设银行",
      "bankNo": "01050000",
      "bankLogoUrl": "https://iqcms.hdfax.com/eif-cms/app/bank/newLogo/CBC76x76.png",
      "singleLimit": "单笔限额400万 单日限额2000万 单月限额10000万",
      "singleLimitAmount": "4000000.00",
      "mobilePhone": "155****5555",
      "isAvailable": 1
    },
    {
      "paymentInstrumentType": 2,
      "paymentInstrumentNo": "QAI00000000000019099",
      "paymentTitle": "建设银行(6555)",
      "cardNo": "621700*********6555",
      "cardType": 1,
      "bankName": "建设银行",
      "bankNo": "01050000",
      "bankLogoUrl": "https://iqcms.hdfax.com/eif-cms/app/bank/newLogo/CBC76x76.png",
      "singleLimit": "单笔限额400万 单日限额2000万 单月限额10000万",
      "singleLimitAmount": "4000000.00",
      "mobilePhone": "155****5555",
      "isAvailable": 1
    },
    {
      "paymentInstrumentType": 2,
      "paymentInstrumentNo": "QAI00000000000019099",
      "paymentTitle": "建设银行(6555)",
      "cardNo": "621700*********6555",
      "cardType": 1,
      "bankName": "建设银行",
      "bankNo": "01050000",
      "bankLogoUrl": "https://iqcms.hdfax.com/eif-cms/app/bank/newLogo/CBC76x76.png",
      "singleLimit": "单笔限额400万 单日限额2000万 单月限额10000万",
      "singleLimitAmount": "4000000.00",
      "mobilePhone": "155****5555",
      "isAvailable": 1
    },
    {
      "paymentInstrumentType": 2,
      "paymentInstrumentNo": "QAI00000000000019099",
      "paymentTitle": "建设银行(6555)",
      "cardNo": "621700*********6555",
      "cardType": 1,
      "bankName": "建设银行",
      "bankNo": "01050000",
      "bankLogoUrl": "https://iqcms.hdfax.com/eif-cms/app/bank/newLogo/CBC76x76.png",
      "singleLimit": "单笔限额400万 单日限额2000万 单月限额10000万",
      "singleLimitAmount": "4000000.00",
      "mobilePhone": "155****5555",
      "isAvailable": 1
    },
    {
      "paymentInstrumentType": 2,
      "paymentInstrumentNo": "QAI00000000000020656",
      "paymentTitle": "农业银行(6222)",
      "cardNo": "622848*********6222",
      "cardType": 1,
      "bankName": "农业银行",
      "bankNo": "01030000",
      "bankLogoUrl": "https://iqcms.hdfax.com/eif-cms/app/bank/newLogo/ABC76x76.png",
      "singleLimit": "单笔限额100万",
      "singleLimitAmount": "1000000.00",
      "mobilePhone": "111****1111",
      "isAvailable": 1
    },
    {
      "paymentInstrumentType": 2,
      "paymentInstrumentNo": "QAI00000000000021345",
      "paymentTitle": "工商银行(6111)",
      "cardNo": "621226*********6111",
      "cardType": 1,
      "bankName": "工商银行",
      "bankNo": "01020000",
      "bankLogoUrl": "https://iqcms.hdfax.com/eif-cms/app/bank/newLogo/ICBC76x76.png",
      "singleLimit": "单笔限额30万 单日限额400万 单月限额6000万",
      "singleLimitAmount": "300000.00",
      "mobilePhone": "155****1245",
      "isAvailable": 1
    }
  ],
  "notAvailablePaymentList": [],
  "needAddCardFlag": false,
  "balancePaymentInstrument": {
    "availableBalance": "12485.74",
    "paymentInstrumentStatus": "2",
    "paymentInstrumentType": "6",
    "paymentTitle": "余额支付",
    "isDefaultPayment": 1,
    "isAvailable": 1
  },
  "payAmount": "100.00",
  "htAppAPI": "https://ht-h5-test.htmimi.com/",
  "availCouponNumber": 0,
  "resultCode": "1000",
  "resultMsg": "调用成功",
  "traceNo": "mtpac10393b4172711544",
  "displayType": "showToast",
  "success": true,
  "useCustMsg": false
}
